textual_fastdatatable/__init__.py
textual_fastdatatable/__main__.py
textual_fastdatatable/backend.py
textual_fastdatatable/column.py
textual_fastdatatable/data_table.py
textual_fastdatatable/format.py
textual_fastdatatable/py.typed
textual_fastdatatable-0.13.0.dist-info/METADATA
textual_fastdatatable-0.13.0.dist-info/WHEEL
textual_fastdatatable-0.13.0.dist-info/licenses/LICENSE
textual_fastdatatable-0.13.0.dist-info/RECORD
