Metadata-Version: 2.4
Name: textual-fastdatatable
Version: 0.13.0
Summary: A performance-focused reimplementation of Textual's DataTable widget, with a pluggable data storage backend.
Project-URL: Repository, https://github.com/tconbeer/textual-fastdatatable
Author-email: Ted Conbeer <tconbeer@users.noreply.github.com>
License-Expression: MIT
License-File: LICENSE
Requires-Python: <3.14,>=3.9
Requires-Dist: numpy<2.1.0,>=2.0.0; python_version < '3.10'
Requires-Dist: numpy<2.3.0,>=2.1.0; python_version >= '3.10'
Requires-Dist: pandas<3,>=2.2.1; python_version < '3.13'
Requires-Dist: pandas<3,>=2.2.3; python_version >= '3.13'
Requires-Dist: pyarrow<22,>=18.1.0
Requires-Dist: textual>=0.89.1
Requires-Dist: tzdata>=2023; sys_platform == 'win32'
Provides-Extra: polars
Requires-Dist: polars<2,>=1; extra == 'polars'
